simple_sketch/README.md
simple_sketch/__init__.py
simple_sketch/simple_sketch.py
simple_sketch/lib/__init__.py
simple_sketch/lib/adt/__init__.py
simple_sketch/lib/adt/tree/__init__.py
simple_sketch/lib/adt/tree/build.py
simple_sketch/lib/adt/tree/paths.py
simple_sketch/lib/adt/tree/walk.py
simple_sketch/lib/adt/tree/search/__init__.py
simple_sketch/lib/adt/tree/search/pattern.py
simple_sketch/lib/adt/tree/transform/__init__.py
simple_sketch/lib/adt/tree/transform/apply.py
simple_sketch/lib/adt/tree/transform/substitute.py
simple_sketch/simple_sketch_cli/__init__.py
simple_sketch/simple_sketch_cli/simple_sketch_cli.py
simple_sketch/simple_sketch_gui/__init__.py
simple_sketch/simple_sketch_gui/simple_sketch_gui.py
simple_sketch/simple_sketch_gui/assets/examples/example-1.yaml
simple_sketch/simple_sketch_gui/assets/examples/example-2.yaml
simple_sketch/simple_sketch_gui/assets/examples/example-3.yaml
simple_sketch/simple_sketch_gui/assets/examples/Advanced-Examples/example-1.yaml
simple_sketch/simple_sketch_gui/assets/examples/Advanced-Examples/example-2.yaml
simple_sketch/simple_sketch_gui/assets/examples/Advanced-Examples/example-3.yaml
simple_sketch/simple_sketch_gui/assets/examples/Array-Examples/example-1.yaml
simple_sketch/simple_sketch_gui/assets/examples/Array-Examples/example-2.yaml
simple_sketch/simple_sketch_gui/assets/examples/Array-Examples/example-3.yaml
simple_sketch/simple_sketch_gui/assets/examples/Basic-Examples/example-1.yaml
simple_sketch/simple_sketch_gui/assets/examples/Basic-Examples/example-2.yaml
simple_sketch/simple_sketch_gui/assets/examples/Basic-Examples/example-3.yaml
simple_sketch/simple_sketch_gui/assets/examples/Basic-Examples/example-4.yaml
simple_sketch/simple_sketch_gui/assets/examples/Basic-Examples/example-5.yaml
simple_sketch/simple_sketch_gui/assets/examples/Basic-Examples/example-6.yaml
simple_sketch/simple_sketch_gui/assets/examples/Basic-Examples/example-7.yaml
simpleSketch-0.0.8.dist-info/LICENSE
simpleSketch-0.0.8.dist-info/METADATA
simpleSketch-0.0.8.dist-info/WHEEL
simpleSketch-0.0.8.dist-info/entry_points.txt
simpleSketch-0.0.8.dist-info/top_level.txt
simpleSketch-0.0.8.dist-info/RECORD
