Metadata-Version: 2.1
Name: simpleSketch
Version: 0.0.8
Summary: Program Synthesis by Sketching
Author-email: Maher Bisan <maherbisan95@gmail.com>
Maintainer-email: Dareen Khair <dareen17.7@gmail.com>, Maher Bisan <maherbisan95@gmail.com>
License: MIT License
Project-URL: Homepage, https://github.com/maher-bisan/SimpleSketch
Project-URL: Bug Tracker, https://github.com/maher-bisan/SimpleSketch/issues
Keywords: SimpleSketch,Synthesis,CEGIS,Program Synthesis,Sketching,PBE
Classifier: Programming Language :: Python :: 3.11
Classifier: Operating System :: OS Independent
Requires-Python: >=3.11
License-File: LICENSE
Requires-Dist: z3-solver ==4.12.2.0
Requires-Dist: lark ==1.1.7
Requires-Dist: pyyaml
Requires-Dist: customtkinter ==5.2.0
Requires-Dist: graphviz ==0.20.1
Provides-Extra: dev
Requires-Dist: build ==1.0.3 ; extra == 'dev'
Requires-Dist: ipykernel ==6.25.2 ; extra == 'dev'
Requires-Dist: mkdocs ==1.5.3 ; extra == 'dev'
Requires-Dist: Pillow ; extra == 'dev'
Requires-Dist: twine ; extra == 'dev'
Provides-Extra: dev-notebook
Requires-Dist: ipykernel ==6.25.2 ; extra == 'dev-notebook'
